charmlibs/snap/__init__.py
charmlibs/snap/_snap.py
charmlibs/snap/_version.py
charmlibs/snap/py.typed
charmlibs_snap-1.0.1.dist-info/METADATA
charmlibs_snap-1.0.1.dist-info/WHEEL
charmlibs_snap-1.0.1.dist-info/RECORD
