Metadata-Version: 2.4
Name: charmlibs-snap
Version: 1.0.1
Summary: The charmlibs.snap package.
Project-URL: Documentation, https://documentation.ubuntu.com/charmlibs/reference/charmlibs/snap/
Project-URL: Repository, https://github.com/canonical/charmlibs
Project-URL: Issues, https://github.com/canonical/charmlibs/issues
Project-URL: Changelog, https://github.com/canonical/charmlibs/blob/main/snap/CHANGELOG.md
Author: The Charm Tech team at Canonical
Classifier: Development Status :: 5 - Production/Stable
Classifier: Intended Audience :: Developers
Classifier: License :: OSI Approved :: Apache Software License
Classifier: Operating System :: POSIX :: Linux
Classifier: Programming Language :: Python :: 3
Requires-Python: >=3.10
Requires-Dist: opentelemetry-api
